netmikio/__init__.py
netmikio/netmikio.py
netmikio-1.0.2.dist-info/LICENSE
netmikio-1.0.2.dist-info/METADATA
netmikio-1.0.2.dist-info/WHEEL
netmikio-1.0.2.dist-info/top_level.txt
netmikio-1.0.2.dist-info/zip-safe
netmikio-1.0.2.dist-info/RECORD
