Metadata-Version: 2.1
Name: netmikio
Version: 1.0.2
Summary: Asynchronous SSH handler based on Netmiko for managing network devices.
Author: Anton Hultberg
Author-email: anton@tpo.se
License-File: LICENSE
Requires-Dist: netmiko>=4.1.2
